{
  "model-schema": [
    {"name": "GENDER", "type": "string"},
    {"name": "AGE", "type": "integer"},
    {"name": "MARITAL_STATUS", "type": "string"},
    {"name": "PROFESSION", "type": "string"},
    {"name": "PRODUCT_LINE", "type": "string"}
  ],
  "model-input": [
    {"id": "Alice", "data": ["F",19,"Single","Professional"]},
    {"id": "Gregory", "data": ["M",57,"Married","Trades"]},
    {"id": "Joanna", "data": ["F",40, "Married", "Executive"]},
    {"id": "Alexander", "data": ["M",36,"Single","Sales"]}
  ],
  "model-prediction-mapping": {
    "0": ["Camping Equipment", "camping.svg"],
    "1": ["Personal Accessories", "accessories.svg"],
    "2": ["Mountaineering Equipment", "mountaineering.svg"],
    "3": ["Golf Equipment", "golfing.svg"],
    "4": ["Outdoor Protection", "outdoor_protection.svg"]
  }
}
